snake_di/__init__.py
snake_di/_container.py
snake_di/_factory.py
snake_di/_factory_group.py
snake_di/_inspector.py
snake_di/_provider.py
snake_di/_service_dict.py
snake_di/_types.py
snake_di/_utils.py
snake_di/pytest.py
snake_di-0.0.3.dist-info/LICENSE
snake_di-0.0.3.dist-info/WHEEL
snake_di-0.0.3.dist-info/METADATA
snake_di-0.0.3.dist-info/RECORD
