Metadata-Version: 2.1
Name: snake-di
Version: 0.0.3
Summary: Simple yet powerful dependency injection framework!
Author-email: Ilya Cherezov <cherezov.ia@phystech.edu>
Requires-Python: >=3.8
Classifier: License :: OSI Approved :: MIT License
Classifier: Programming Language :: Python :: 3 :: Only
Classifier: Programming Language :: Python :: 3.8
Classifier: Programming Language :: Python :: 3.9
Classifier: Programming Language :: Python :: 3.10
Classifier: Programming Language :: Python :: 3.11
Requires-Dist: typing_extensions
Project-URL: Github, https://github.com/l1onsun/snake_di
